fleetone/__init__.py
fleetone/fleet.py
fleettwo-0.0.2.dist-info/METADATA
fleettwo-0.0.2.dist-info/WHEEL
fleettwo-0.0.2.dist-info/top_level.txt
fleettwo-0.0.2.dist-info/RECORD
