Metadata-Version: 2.1
Name: fleettwo
Version: 0.0.2
Summary: Suraj Bherwani's helper function
Home-page: UNKNOWN
Author: Suraj Bherwani
Author-email: <avengenation7@gmail.com>
License: UNKNOWN
Platform: UNKNOWN
Classifier: Development Status :: 1 - Planning
Classifier: Intended Audience :: Developers
Classifier: Programming Language :: Python :: 3
Classifier: Operating System :: Unix
Classifier: Operating System :: MacOS :: MacOS X
Classifier: Operating System :: Microsoft :: Windows
Requires-Dist: tensorflow
Requires-Dist: bokeh
Requires-Dist: numpy
